{
  "variables": [
    {
      "name": "$selector-button",
      "value": ".button",
      "compiledValue": ".button"
    },
    {
      "name": "$modifier-button-strong",
      "value": ".is-strong",
      "compiledValue": ".is-strong"
    },
    {
      "name": "$modifier-button-round",
      "value": ".is-round",
      "compiledValue": ".is-round"
    },
    {
      "name": "$modifier-button-floating",
      "value": ".is-floating",
      "compiledValue": ".is-floating"
    },
    {
      "name": "$modifier-button-square",
      "value": ".is-square",
      "compiledValue": ".is-square"
    },
    {
      "name": "$modifier-button-circle",
      "value": ".is-circle",
      "compiledValue": ".is-circle"
    },
    {
      "name": "$modifier-button-disabled",
      "value": ".is-disabled",
      "compiledValue": ".is-disabled"
    },
    {
      "name": "$modifier-button-plain",
      "value": ".is-plain",
      "compiledValue": ".is-plain"
    },
    {
      "name": "$modifier-button-outline",
      "value": ".is-outline",
      "compiledValue": ".is-outline"
    },
    {
      "name": "$modifier-button-melt",
      "value": ".is-melt",
      "compiledValue": ".is-melt"
    },
    {
      "name": "$modifier-button-primary",
      "value": ".is-primary",
      "compiledValue": ".is-primary"
    },
    {
      "name": "$modifier-button-info",
      "value": ".is-info",
      "compiledValue": ".is-info"
    },
    {
      "name": "$modifier-button-success",
      "value": ".is-success",
      "compiledValue": ".is-success"
    },
    {
      "name": "$modifier-button-warning",
      "value": ".is-warning",
      "compiledValue": ".is-warning"
    },
    {
      "name": "$modifier-button-danger",
      "value": ".is-danger",
      "compiledValue": ".is-danger"
    },
    {
      "name": "$modifier-button-angle-right",
      "value": ".is-angle-right",
      "compiledValue": ".is-angle-right"
    },
    {
      "name": "$modifier-button-angle-left",
      "value": ".is-angle-left",
      "compiledValue": ".is-angle-left"
    },
    {
      "name": "$modifier-button-angle-up",
      "value": ".is-angle-up",
      "compiledValue": ".is-angle-up"
    },
    {
      "name": "$modifier-button-angle-down",
      "value": ".is-angle-down",
      "compiledValue": ".is-angle-down"
    },
    {
      "name": "$button-padding",
      "value": "0.5em 1em",
      "compiledValue": "0.5em 1em"
    },
    {
      "name": "$button-border-width",
      "value": "$global-border-width",
      "compiledValue": "1px"
    },
    {
      "name": "$button-border-radius",
      "value": "$radius-sm",
      "compiledValue": "3px"
    },
    {
      "name": "$button-paint-color",
      "value": "$convert-button-paint-color",
      "compiledValue": "var(--button-paint-color)"
    },
    {
      "name": "$button-line-height",
      "value": "$line-height-md",
      "compiledValue": "1.5"
    },
    {
      "name": "$button-transition",
      "value": "$global-transition",
      "compiledValue": "ease-out 0.12s"
    },
    {
      "name": "$button-focus-shadow",
      "value": "$global-focus-shadow-size $convert-focus-alpha",
      "compiledValue": "0 0 0 4px var(--focus-alpha)"
    },
    {
      "name": "$button-strong-font-weight",
      "value": "$font-weight-strong",
      "compiledValue": "700"
    },
    {
      "name": "$button-round-border-radius",
      "value": "$radius-full",
      "compiledValue": "999em"
    },
    {
      "name": "$button-floating-shadow",
      "value": "$global-floating-shadow-size $convert-shadow-alpha",
      "compiledValue": "0 2px 6px 0 var(--shadow-alpha)"
    },
    {
      "name": "$button-floating-hover-shadow",
      "value": "$global-floating-hover-shadow-size $convert-shadow-alpha",
      "compiledValue": "0 4px 12px 0 var(--shadow-alpha)"
    },
    {
      "name": "$button-floating-focus-shadow",
      "value": "$global-focus-shadow-size $convert-focus-alpha, $global-floating-hover-shadow-size $convert-shadow-alpha",
      "compiledValue": "0 0 0 4px var(--focus-alpha), 0 4px 12px 0 var(--shadow-alpha)"
    },
    {
      "name": "$button-disabled-background-color",
      "value": "$convert-disabled-background-color",
      "compiledValue": "var(--disabled-background-color)"
    },
    {
      "name": "$button-disabled-color",
      "value": "$convert-disabled-color",
      "compiledValue": "var(--disabled-color)"
    },
    {
      "name": "$button-square-width",
      "value": "calc(2.5em + #{$global-border-width} * 2)",
      "compiledValue": "calc(2.5em + 1px * 2)"
    },
    {
      "name": "$button-square-height",
      "value": "calc(2.5em + #{$global-border-width} * 2)",
      "compiledValue": "calc(2.5em + 1px * 2)"
    },
    {
      "name": "$button-square-border-radius",
      "value": "$radius-sm",
      "compiledValue": "3px"
    },
    {
      "name": "$button-circle-width",
      "value": "calc(2.5em + #{$global-border-width} * 2)",
      "compiledValue": "calc(2.5em + 1px * 2)"
    },
    {
      "name": "$button-circle-height",
      "value": "calc(2.5em + #{$global-border-width} * 2)",
      "compiledValue": "calc(2.5em + 1px * 2)"
    },
    {
      "name": "$button-circle-border-radius",
      "value": "$radius-full",
      "compiledValue": "999em"
    },
    {
      "name": "$button-plain-background-color",
      "value": "$convert-background-2",
      "compiledValue": "var(--background-2)"
    },
    {
      "name": "$button-plain-hover-background-color",
      "value": "$convert-background-4",
      "compiledValue": "var(--background-4)"
    },
    {
      "name": "$button-plain-primary-background-color",
      "value": "$convert-primary",
      "compiledValue": "var(--primary)"
    },
    {
      "name": "$button-plain-primary-hover-background-color",
      "value": "$convert-primary-darken",
      "compiledValue": "var(--primary-darken)"
    },
    {
      "name": "$button-plain-info-background-color",
      "value": "$convert-info",
      "compiledValue": "var(--info)"
    },
    {
      "name": "$button-plain-info-hover-background-color",
      "value": "$convert-info-darken",
      "compiledValue": "var(--info-darken)"
    },
    {
      "name": "$button-plain-success-background-color",
      "value": "$convert-success",
      "compiledValue": "var(--success)"
    },
    {
      "name": "$button-plain-success-hover-background-color",
      "value": "$convert-success-darken",
      "compiledValue": "var(--success-darken)"
    },
    {
      "name": "$button-plain-warning-background-color",
      "value": "$convert-warning",
      "compiledValue": "var(--warning)"
    },
    {
      "name": "$button-plain-warning-hover-background-color",
      "value": "$convert-warning-darken",
      "compiledValue": "var(--warning-darken)"
    },
    {
      "name": "$button-plain-danger-background-color",
      "value": "$convert-danger",
      "compiledValue": "var(--danger)"
    },
    {
      "name": "$button-plain-danger-hover-background-color",
      "value": "$convert-danger-darken",
      "compiledValue": "var(--danger-darken)"
    },
    {
      "name": "$button-plain-primary-floating-shadow",
      "value": "$global-floating-shadow-size $convert-shadow-primary-alpha",
      "compiledValue": "0 2px 6px 0 var(--shadow-primary-alpha)"
    },
    {
      "name": "$button-plain-primary-floating-hover-shadow",
      "value": "$global-floating-hover-shadow-size $convert-shadow-primary-alpha",
      "compiledValue": "0 4px 12px 0 var(--shadow-primary-alpha)"
    },
    {
      "name": "$button-plain-primary-floating-focus-shadow",
      "value": "$global-focus-shadow-size $convert-focus-alpha, $global-floating-hover-shadow-size $convert-shadow-primary-alpha",
      "compiledValue": "0 0 0 4px var(--focus-alpha), 0 4px 12px 0 var(--shadow-primary-alpha)"
    },
    {
      "name": "$button-plain-info-floating-shadow",
      "value": "$global-floating-shadow-size $convert-shadow-info-alpha",
      "compiledValue": "0 2px 6px 0 var(--shadow-info-alpha)"
    },
    {
      "name": "$button-plain-info-floating-hover-shadow",
      "value": "$global-floating-hover-shadow-size $convert-shadow-info-alpha",
      "compiledValue": "0 4px 12px 0 var(--shadow-info-alpha)"
    },
    {
      "name": "$button-plain-info-floating-focus-shadow",
      "value": "$global-focus-shadow-size $convert-focus-alpha, $global-floating-hover-shadow-size $convert-shadow-info-alpha",
      "compiledValue": "0 0 0 4px var(--focus-alpha), 0 4px 12px 0 var(--shadow-info-alpha)"
    },
    {
      "name": "$button-plain-success-floating-shadow",
      "value": "$global-floating-shadow-size $convert-shadow-success-alpha",
      "compiledValue": "0 2px 6px 0 var(--shadow-success-alpha)"
    },
    {
      "name": "$button-plain-success-floating-hover-shadow",
      "value": "$global-floating-hover-shadow-size $convert-shadow-success-alpha",
      "compiledValue": "0 4px 12px 0 var(--shadow-success-alpha)"
    },
    {
      "name": "$button-plain-success-floating-focus-shadow",
      "value": "$global-focus-shadow-size $convert-focus-alpha, $global-floating-hover-shadow-size $convert-shadow-success-alpha",
      "compiledValue": "0 0 0 4px var(--focus-alpha), 0 4px 12px 0 var(--shadow-success-alpha)"
    },
    {
      "name": "$button-plain-warning-floating-shadow",
      "value": "$global-floating-shadow-size $convert-shadow-warning-alpha",
      "compiledValue": "0 2px 6px 0 var(--shadow-warning-alpha)"
    },
    {
      "name": "$button-plain-warning-floating-hover-shadow",
      "value": "$global-floating-hover-shadow-size $convert-shadow-warning-alpha",
      "compiledValue": "0 4px 12px 0 var(--shadow-warning-alpha)"
    },
    {
      "name": "$button-plain-warning-floating-focus-shadow",
      "value": "$global-focus-shadow-size $convert-focus-alpha, $global-floating-hover-shadow-size $convert-shadow-warning-alpha",
      "compiledValue": "0 0 0 4px var(--focus-alpha), 0 4px 12px 0 var(--shadow-warning-alpha)"
    },
    {
      "name": "$button-plain-danger-floating-shadow",
      "value": "$global-floating-shadow-size $convert-shadow-danger-alpha",
      "compiledValue": "0 2px 6px 0 var(--shadow-danger-alpha)"
    },
    {
      "name": "$button-plain-danger-floating-hover-shadow",
      "value": "$global-floating-hover-shadow-size $convert-shadow-danger-alpha",
      "compiledValue": "0 4px 12px 0 var(--shadow-danger-alpha)"
    },
    {
      "name": "$button-plain-danger-floating-focus-shadow",
      "value": "$global-focus-shadow-size $convert-focus-alpha, $global-floating-hover-shadow-size $convert-shadow-danger-alpha",
      "compiledValue": "0 0 0 4px var(--focus-alpha), 0 4px 12px 0 var(--shadow-danger-alpha)"
    },
    {
      "name": "$button-outline-background-color",
      "value": "$convert-background",
      "compiledValue": "var(--background)"
    },
    {
      "name": "$button-outline-border-color",
      "value": "$convert-border",
      "compiledValue": "var(--border)"
    },
    {
      "name": "$button-outline-hover-background-color",
      "value": "$convert-background-2",
      "compiledValue": "var(--background-2)"
    },
    {
      "name": "$button-outline-primary-border-color",
      "value": "$convert-primary",
      "compiledValue": "var(--primary)"
    },
    {
      "name": "$button-outline-primary-color",
      "value": "$convert-primary-strong",
      "compiledValue": "var(--primary-strong)"
    },
    {
      "name": "$button-outline-primary-hover-background-color",
      "value": "$convert-primary",
      "compiledValue": "var(--primary)"
    },
    {
      "name": "$button-outline-info-border-color",
      "value": "$convert-info",
      "compiledValue": "var(--info)"
    },
    {
      "name": "$button-outline-info-color",
      "value": "$convert-info-strong",
      "compiledValue": "var(--info-strong)"
    },
    {
      "name": "$button-outline-info-hover-background-color",
      "value": "$convert-info",
      "compiledValue": "var(--info)"
    },
    {
      "name": "$button-outline-success-border-color",
      "value": "$convert-success",
      "compiledValue": "var(--success)"
    },
    {
      "name": "$button-outline-success-color",
      "value": "$convert-success-strong",
      "compiledValue": "var(--success-strong)"
    },
    {
      "name": "$button-outline-success-hover-background-color",
      "value": "$convert-success",
      "compiledValue": "var(--success)"
    },
    {
      "name": "$button-outline-warning-border-color",
      "value": "$convert-warning",
      "compiledValue": "var(--warning)"
    },
    {
      "name": "$button-outline-warning-color",
      "value": "$convert-warning-strong",
      "compiledValue": "var(--warning-strong)"
    },
    {
      "name": "$button-outline-warning-hover-background-color",
      "value": "$convert-warning",
      "compiledValue": "var(--warning)"
    },
    {
      "name": "$button-outline-danger-border-color",
      "value": "$convert-danger",
      "compiledValue": "var(--danger)"
    },
    {
      "name": "$button-outline-danger-color",
      "value": "$convert-danger-strong",
      "compiledValue": "var(--danger-strong)"
    },
    {
      "name": "$button-outline-danger-hover-background-color",
      "value": "$convert-danger",
      "compiledValue": "var(--danger)"
    },
    {
      "name": "$button-melt-hover-background-color",
      "value": "$convert-background-alpha",
      "compiledValue": "var(--background-alpha)"
    },
    {
      "name": "$button-melt-primary-color",
      "value": "$convert-primary-strong",
      "compiledValue": "var(--primary-strong)"
    },
    {
      "name": "$button-melt-info-color",
      "value": "$convert-info-strong",
      "compiledValue": "var(--info-strong)"
    },
    {
      "name": "$button-melt-success-color",
      "value": "$convert-success-strong",
      "compiledValue": "var(--success-strong)"
    },
    {
      "name": "$button-melt-warning-color",
      "value": "$convert-warning-strong",
      "compiledValue": "var(--warning-strong)"
    },
    {
      "name": "$button-melt-danger-color",
      "value": "$convert-danger-strong",
      "compiledValue": "var(--danger-strong)"
    },
    {
      "name": "$button-angle-size",
      "value": "0.5em",
      "compiledValue": "0.5em"
    },
    {
      "name": "$button-angle-border-width",
      "value": "$global-border-width * 2",
      "compiledValue": "2px"
    },
    {
      "name": "$button-angle-border-color",
      "value": "$convert-border-1",
      "compiledValue": "var(--border-1)"
    }
  ],
  "mixins": [
    {
      "name": "musubii-style-button",
      "parameters": []
    },
    {
      "name": "musubii-style-button-strong",
      "parameters": []
    },
    {
      "name": "musubii-style-button-disabled",
      "parameters": []
    },
    {
      "name": "musubii-style-button-round",
      "parameters": []
    },
    {
      "name": "musubii-style-button-floating",
      "parameters": []
    },
    {
      "name": "musubii-style-button-square",
      "parameters": []
    },
    {
      "name": "musubii-style-button-circle",
      "parameters": []
    },
    {
      "name": "musubii-style-button-plain",
      "parameters": []
    },
    {
      "name": "musubii-style-button-plain-primary",
      "parameters": []
    },
    {
      "name": "musubii-style-button-plain-info",
      "parameters": []
    },
    {
      "name": "musubii-style-button-plain-success",
      "parameters": []
    },
    {
      "name": "musubii-style-button-plain-warning",
      "parameters": []
    },
    {
      "name": "musubii-style-button-plain-danger",
      "parameters": []
    },
    {
      "name": "musubii-style-button-plain-disabled",
      "parameters": []
    },
    {
      "name": "musubii-style-button-plain-primary-floating",
      "parameters": []
    },
    {
      "name": "musubii-style-button-plain-info-floating",
      "parameters": []
    },
    {
      "name": "musubii-style-button-plain-success-floating",
      "parameters": []
    },
    {
      "name": "musubii-style-button-plain-warning-floating",
      "parameters": []
    },
    {
      "name": "musubii-style-button-plain-danger-floating",
      "parameters": []
    },
    {
      "name": "musubii-style-button-outline",
      "parameters": []
    },
    {
      "name": "musubii-style-button-outline-primary",
      "parameters": []
    },
    {
      "name": "musubii-style-button-outline-info",
      "parameters": []
    },
    {
      "name": "musubii-style-button-outline-success",
      "parameters": []
    },
    {
      "name": "musubii-style-button-outline-warning",
      "parameters": []
    },
    {
      "name": "musubii-style-button-outline-danger",
      "parameters": []
    },
    {
      "name": "musubii-style-button-outline-disabled",
      "parameters": []
    },
    {
      "name": "musubii-style-button-melt",
      "parameters": []
    },
    {
      "name": "musubii-style-button-melt-primary",
      "parameters": []
    },
    {
      "name": "musubii-style-button-melt-info",
      "parameters": []
    },
    {
      "name": "musubii-style-button-melt-success",
      "parameters": []
    },
    {
      "name": "musubii-style-button-melt-warning",
      "parameters": []
    },
    {
      "name": "musubii-style-button-melt-danger",
      "parameters": []
    },
    {
      "name": "musubii-style-button-melt-disabled",
      "parameters": []
    },
    {
      "name": "musubii-style-button-angle",
      "parameters": []
    },
    {
      "name": "musubii-style-button-angle-right",
      "parameters": []
    },
    {
      "name": "musubii-style-button-angle-left",
      "parameters": []
    },
    {
      "name": "musubii-style-button-angle-up",
      "parameters": []
    },
    {
      "name": "musubii-style-button-angle-down",
      "parameters": []
    },
    {
      "name": "musubii-style-button-angle-color-current",
      "parameters": []
    }
  ]
}